nonebot_plugin_delta_password/__init__.py
nonebot_plugin_delta_password/config.py
nonebot_plugin_delta_password/handler.py
nonebot_plugin_delta_password-1.0.1.dist-info/licenses/LICENSE
nonebot_plugin_delta_password-1.0.1.dist-info/METADATA
nonebot_plugin_delta_password-1.0.1.dist-info/WHEEL
nonebot_plugin_delta_password-1.0.1.dist-info/top_level.txt
nonebot_plugin_delta_password-1.0.1.dist-info/RECORD
