Metadata-Version: 2.4
Name: nonebot-plugin-delta-password
Version: 1.0.1
Summary: 三角洲行动每日密码查询插件
Author-email: mmxd12 <2529464880@qq.com>
Classifier: License :: OSI Approved :: MIT License
Classifier: Operating System :: OS Independent
Classifier: Programming Language :: Python :: 3.9
Classifier: Programming Language :: Python :: 3.10
Classifier: Programming Language :: Python :: 3.11
Classifier: Programming Language :: Python :: 3.12
Requires-Python: >=3.9
License-File: LICENSE
Requires-Dist: nonebot2>=2.4.4
Requires-Dist: nonebot-adapter-qq>=1.6.5
Requires-Dist: httpx>=0.28.1
Requires-Dist: pydantic>=2.0.0
Dynamic: license-file
